comfoair/__init__.py
comfoair/asyncio.py
comfoair/sync.py
pycomfoair-0.2.0.dist-info/LICENSE
pycomfoair-0.2.0.dist-info/METADATA
pycomfoair-0.2.0.dist-info/WHEEL
pycomfoair-0.2.0.dist-info/RECORD
