Metadata-Version: 2.1
Name: pycomfoair
Version: 0.2.0
Summary: Interface for Zehnder ComfoAir 350 ventilation units
Home-page: https://github.com/mtdcr/pycomfoair
License: MIT
Author: Andreas Oberritter
Author-email: obi@saftware.de
Requires-Python: >=3.8,<4.0
Classifier: Intended Audience :: Developers
Classifier: License :: OSI Approved :: MIT License
Classifier: Programming Language :: Python :: 3
Classifier: Programming Language :: Python :: 3.8
Classifier: Programming Language :: Python :: 3.9
Classifier: Programming Language :: Python :: 3.10
Classifier: Programming Language :: Python :: 3.11
Classifier: Programming Language :: Python :: 3.12
Classifier: Topic :: Home Automation
Requires-Dist: async-timeout (>=4.0.3)
Requires-Dist: bitstring (>=3.1.9)
Requires-Dist: pyserial-asyncio-fast (>=0.14,<0.15)
Project-URL: Repository, https://github.com/mtdcr/pycomfoair
